litemapy/__init__.py
litemapy/boxes.py
litemapy/deprecation.py
litemapy/info.py
litemapy/minecraft.py
litemapy/schematic.py
litemapy/storage.py
litemapy-0.10.0b0.dist-info/LICENSE
litemapy-0.10.0b0.dist-info/METADATA
litemapy-0.10.0b0.dist-info/WHEEL
litemapy-0.10.0b0.dist-info/top_level.txt
litemapy-0.10.0b0.dist-info/RECORD
