Metadata-Version: 2.1
Name: litemapy
Version: 0.10.0b0
Summary: Read and write Litematica's Minecraft schematics files
Home-page: https://github.com/SmylerMC/litemapy
Author: SmylerMC
Author-email: smyler@mail.com
License: GNU General Public License v3 (GPLv3)
Classifier: Development Status :: 4 - Beta
Classifier: Intended Audience :: Other Audience
Classifier: License :: OSI Approved :: GNU General Public License v3 (GPLv3)
Classifier: Operating System :: OS Independent
Classifier: Programming Language :: Python :: 3
Classifier: Topic :: Games/Entertainment
Requires-Python: >=3.9
License-File: LICENSE
Requires-Dist: nbtlib>=2.0.3
Requires-Dist: typing-extensions
